[{"_id": {"$oid": "62e089bffb2ae0ba5142e540"}, "name": "django_migrations", "auto": {"field_names": ["id"], "seq": 16}},{"_id": {"$oid": "62e089c3fb2ae0ba5142e55a"}, "name": "users_user", "auto": {"field_names": ["id"], "seq": 12}},{"_id": {"$oid": "62e089c3fb2ae0ba5142e55f"}, "name": "users_timezone", "auto": {"field_names": ["id"], "seq": 4}},{"_id": {"$oid": "62e089c4fb2ae0ba5142e565"}, "name": "users_visitor", "auto": {"field_names": ["id"], "seq": 2}},{"_id": {"$oid": "62e089c5fb2ae0ba5142e56f"}, "name": "django_content_type", "auto": {"field_names": ["id"], "seq": 15}},{"_id": {"$oid": "62e089c5fb2ae0ba5142e579"}, "name": "django_admin_log", "auto": {"field_names": ["id"], "seq": 0}},{"_id": {"$oid": "62e089c6fb2ae0ba5142e587"}, "name": "auth_permission", "auto": {"field_names": ["id"], "seq": 45}},{"_id": {"$oid": "62e089c7fb2ae0ba5142e58d"}, "name": "auth_group", "auto": {"field_names": ["id"], "seq": 0}},{"_id": {"$oid": "62e089c7fb2ae0ba5142e592"}, "name": "auth_group_permissions", "auto": {"field_names": ["id"], "seq": 0}},{"_id": {"$oid": "62e089c9fb2ae0ba5142e5b2"}, "name": "events_button", "auto": {"field_names": ["id"], "seq": 0}},{"_id": {"$oid": "62e089cafb2ae0ba5142e5b8"}, "name": "events_deniedaccess", "auto": {"field_names": ["id"], "seq": 0}},{"_id": {"$oid": "62e089cafb2ae0ba5142e5bf"}, "name": "events_eventsduration", "auto": {"field_names": ["id"], "seq": 1}},{"_id": {"$oid": "62e089cafb2ae0ba5142e5c4"}, "name": "events_movement", "auto": {"field_names": ["id"], "seq": 0}},{"_id": {"$oid": "62e089cbfb2ae0ba5142e5c9"}, "name": "events_movementtimezone", "auto": {"field_names": ["id"], "seq": 1}},{"_id": {"$oid": "62e089cbfb2ae0ba5142e5d0"}, "name": "events_permittedaccess", "auto": {"field_names": ["id"], "seq": 0}},{"_id": {"$oid": "62e089cbfb2ae0ba5142e5d8"}, "name": "events_webopendoor", "auto": {"field_names": ["id"], "seq": 0}},]