[{"_id": {"$oid": "62e089ce80981d6a58e0ce9c"}, "id": 1, "name": "Can add log entry", "content_type_id": 1, "codename": "add_logentry"},{"_id": {"$oid": "62e089cf80981d6a58e0ce9d"}, "id": 2, "name": "Can change log entry", "content_type_id": 1, "codename": "change_logentry"},{"_id": {"$oid": "62e089cf80981d6a58e0ce9e"}, "id": 3, "name": "Can delete log entry", "content_type_id": 1, "codename": "delete_logentry"},{"_id": {"$oid": "62e089d080981d6a58e0cea1"}, "id": 4, "name": "Can add permission", "content_type_id": 2, "codename": "add_permission"},{"_id": {"$oid": "62e089d080981d6a58e0cea2"}, "id": 5, "name": "Can change permission", "content_type_id": 2, "codename": "change_permission"},{"_id": {"$oid": "62e089d080981d6a58e0cea3"}, "id": 6, "name": "Can delete permission", "content_type_id": 2, "codename": "delete_permission"},{"_id": {"$oid": "62e089d180981d6a58e0cea4"}, "id": 7, "name": "Can add group", "content_type_id": 3, "codename": "add_group"},{"_id": {"$oid": "62e089d180981d6a58e0cea5"}, "id": 8, "name": "Can change group", "content_type_id": 3, "codename": "change_group"},{"_id": {"$oid": "62e089d180981d6a58e0cea6"}, "id": 9, "name": "Can delete group", "content_type_id": 3, "codename": "delete_group"},{"_id": {"$oid": "62e089d180981d6a58e0cea8"}, "id": 10, "name": "Can add content type", "content_type_id": 4, "codename": "add_contenttype"},{"_id": {"$oid": "62e089d180981d6a58e0cea9"}, "id": 11, "name": "Can change content type", "content_type_id": 4, "codename": "change_contenttype"},{"_id": {"$oid": "62e089d180981d6a58e0ceaa"}, "id": 12, "name": "Can delete content type", "content_type_id": 4, "codename": "delete_contenttype"},{"_id": {"$oid": "62e089d280981d6a58e0ceac"}, "id": 13, "name": "Can add session", "content_type_id": 5, "codename": "add_session"},{"_id": {"$oid": "62e089d280981d6a58e0cead"}, "id": 14, "name": "Can change session", "content_type_id": 5, "codename": "change_session"},{"_id": {"$oid": "62e089d280981d6a58e0ceae"}, "id": 15, "name": "Can delete session", "content_type_id": 5, "codename": "delete_session"},{"_id": {"$oid": "62e089d480981d6a58e0ceb6"}, "id": 16, "name": "Can add button", "content_type_id": 6, "codename": "add_button"},{"_id": {"$oid": "62e089d480981d6a58e0ceb7"}, "id": 17, "name": "Can change button", "content_type_id": 6, "codename": "change_button"},{"_id": {"$oid": "62e089d480981d6a58e0ceb8"}, "id": 18, "name": "Can delete button", "content_type_id": 6, "codename": "delete_button"},{"_id": {"$oid": "62e089d580981d6a58e0ceb9"}, "id": 19, "name": "Can add denied access", "content_type_id": 7, "codename": "add_deniedaccess"},{"_id": {"$oid": "62e089d580981d6a58e0ceba"}, "id": 20, "name": "Can change denied access", "content_type_id": 7, "codename": "change_deniedaccess"},{"_id": {"$oid": "62e089d580981d6a58e0cebb"}, "id": 21, "name": "Can delete denied access", "content_type_id": 7, "codename": "delete_deniedaccess"},{"_id": {"$oid": "62e089d580981d6a58e0cebc"}, "id": 22, "name": "Can add events duration", "content_type_id": 8, "codename": "add_eventsduration"},{"_id": {"$oid": "62e089d580981d6a58e0cebd"}, "id": 23, "name": "Can change events duration", "content_type_id": 8, "codename": "change_eventsduration"},{"_id": {"$oid": "62e089d580981d6a58e0cebe"}, "id": 24, "name": "Can delete events duration", "content_type_id": 8, "codename": "delete_eventsduration"},{"_id": {"$oid": "62e089d580981d6a58e0cebf"}, "id": 25, "name": "Can add movement", "content_type_id": 9, "codename": "add_movement"},{"_id": {"$oid": "62e089d580981d6a58e0cec0"}, "id": 26, "name": "Can change movement", "content_type_id": 9, "codename": "change_movement"},{"_id": {"$oid": "62e089d580981d6a58e0cec1"}, "id": 27, "name": "Can delete movement", "content_type_id": 9, "codename": "delete_movement"},{"_id": {"$oid": "62e089d580981d6a58e0cec2"}, "id": 28, "name": "Can add movement time zone", "content_type_id": 10, "codename": "add_movementtimezone"},{"_id": {"$oid": "62e089d680981d6a58e0cec3"}, "id": 29, "name": "Can change movement time zone", "content_type_id": 10, "codename": "change_movementtimezone"},{"_id": {"$oid": "62e089d680981d6a58e0cec4"}, "id": 30, "name": "Can delete movement time zone", "content_type_id": 10, "codename": "delete_movementtimezone"},{"_id": {"$oid": "62e089d680981d6a58e0cec5"}, "id": 31, "name": "Can add permitted access", "content_type_id": 11, "codename": "add_permittedaccess"},{"_id": {"$oid": "62e089d680981d6a58e0cec6"}, "id": 32, "name": "Can change permitted access", "content_type_id": 11, "codename": "change_permittedaccess"},{"_id": {"$oid": "62e089d680981d6a58e0cec7"}, "id": 33, "name": "Can delete permitted access", "content_type_id": 11, "codename": "delete_permittedaccess"},{"_id": {"$oid": "62e089d680981d6a58e0cec8"}, "id": 34, "name": "Can add web open door", "content_type_id": 12, "codename": "add_webopendoor"},{"_id": {"$oid": "62e089d780981d6a58e0cec9"}, "id": 35, "name": "Can change web open door", "content_type_id": 12, "codename": "change_webopendoor"},{"_id": {"$oid": "62e089d780981d6a58e0ceca"}, "id": 36, "name": "Can delete web open door", "content_type_id": 12, "codename": "delete_webopendoor"},{"_id": {"$oid": "62e089d880981d6a58e0cece"}, "id": 37, "name": "Can add user", "content_type_id": 13, "codename": "add_user"},{"_id": {"$oid": "62e089d880981d6a58e0cecf"}, "id": 38, "name": "Can change user", "content_type_id": 13, "codename": "change_user"},{"_id": {"$oid": "62e089d980981d6a58e0ced0"}, "id": 39, "name": "Can delete user", "content_type_id": 13, "codename": "delete_user"},{"_id": {"$oid": "62e089d980981d6a58e0ced1"}, "id": 40, "name": "Can add time zone", "content_type_id": 14, "codename": "add_timezone"},{"_id": {"$oid": "62e089d980981d6a58e0ced2"}, "id": 41, "name": "Can change time zone", "content_type_id": 14, "codename": "change_timezone"},{"_id": {"$oid": "62e089d980981d6a58e0ced3"}, "id": 42, "name": "Can delete time zone", "content_type_id": 14, "codename": "delete_timezone"},{"_id": {"$oid": "62e089d980981d6a58e0ced4"}, "id": 43, "name": "Can add visitor", "content_type_id": 15, "codename": "add_visitor"},{"_id": {"$oid": "62e089d980981d6a58e0ced5"}, "id": 44, "name": "Can change visitor", "content_type_id": 15, "codename": "change_visitor"},{"_id": {"$oid": "62e089d980981d6a58e0ced6"}, "id": 45, "name": "Can delete visitor", "content_type_id": 15, "codename": "delete_visitor"},]